validate_mail.py
validate_mail-1.1.dist-info/LICENSE.txt
validate_mail-1.1.dist-info/METADATA
validate_mail-1.1.dist-info/WHEEL
validate_mail-1.1.dist-info/top_level.txt
validate_mail-1.1.dist-info/RECORD
