Metadata-Version: 2.1
Name: validate-mail
Version: 1.1
Summary: Validating the e-mail ID passed
Home-page: UNKNOWN
Author: Maria Irudaya Regilan J
Author-email: britsa.tech@gmail.com
License: UNKNOWN
Platform: UNKNOWN
Classifier: Programming Language :: Python :: 3.5
Classifier: Programming Language :: Python :: 3.6
Classifier: Programming Language :: Python :: 3.7
Classifier: Programming Language :: Python :: 3.8
Classifier: Operating System :: OS Independent
